rvvsuite/__init__.py
rvvsuite/assembler/__init__.py
rvvsuite/assembler/parser.py
rvvsuite/assembler/translator.py
rvvsuite/common/__init__.py
rvvsuite/common/helpers.py
rvvsuite/common/icb.py
rvvsuite/common/supported_features.py
rvvsuite/common/vector.py
rvvsuite/generator/__init__.py
rvvsuite/generator/confparser.py
rvvsuite/generator/ga.py
rvvsuite/generator/init_data_generator.py
rvvsuite/generator/vrtg.py
rvvsuite/simulator/__init__.py
rvvsuite/simulator/simulator.py
rvvsuite-0.0.8.dist-info/LICENSE.txt
rvvsuite-0.0.8.dist-info/METADATA
rvvsuite-0.0.8.dist-info/WHEEL
rvvsuite-0.0.8.dist-info/top_level.txt
rvvsuite-0.0.8.dist-info/RECORD
