Metadata-Version: 2.2
Name: rvvsuite
Version: 0.0.8
Summary: A set of tools for developing RISC-V Vector IP includes Random Test Generator (RTG), Assembler, and Simulator
Home-page: https://github.com/khiemnb153/rvvsuite
Author: Nguyen Binh Khiem
Author-email: khiemnb153@gmail.com
Classifier: Programming Language :: Python :: 3
Classifier: License :: OSI Approved :: MIT License
Classifier: Operating System :: OS Independent
Requires-Python: >=3.13
License-File: LICENSE.txt
Dynamic: author
Dynamic: author-email
Dynamic: classifier
Dynamic: description
Dynamic: description-content-type
Dynamic: home-page
Dynamic: requires-python
Dynamic: summary
